typedb/__init__.py
typedb/driver.py
typedb/native_driver_python.so
typedb/native_driver_wrapper.py
typedb/api/__init__.py
typedb/api/answer/__init__.py
typedb/api/answer/concept_document_iterator.py
typedb/api/answer/concept_row.py
typedb/api/answer/concept_row_iterator.py
typedb/api/answer/ok_query_answer.py
typedb/api/answer/query_answer.py
typedb/api/answer/query_type.py
typedb/api/concept/__init__.py
typedb/api/concept/concept.py
typedb/api/concept/instance/__init__.py
typedb/api/concept/instance/attribute.py
typedb/api/concept/instance/entity.py
typedb/api/concept/instance/instance.py
typedb/api/concept/instance/relation.py
typedb/api/concept/type/__init__.py
typedb/api/concept/type/attribute_type.py
typedb/api/concept/type/entity_type.py
typedb/api/concept/type/relation_type.py
typedb/api/concept/type/role_type.py
typedb/api/concept/type/type.py
typedb/api/concept/value/__init__.py
typedb/api/concept/value/value.py
typedb/api/connection/__init__.py
typedb/api/connection/credentials.py
typedb/api/connection/database.py
typedb/api/connection/driver.py
typedb/api/connection/driver_options.py
typedb/api/connection/query_options.py
typedb/api/connection/transaction.py
typedb/api/connection/transaction_options.py
typedb/api/user/__init__.py
typedb/api/user/user.py
typedb/common/__init__.py
typedb/common/datetime.py
typedb/common/duration.py
typedb/common/exception.py
typedb/common/iterator_wrapper.py
typedb/common/native_wrapper.py
typedb/common/promise.py
typedb/common/validation.py
typedb/concept/__init__.py
typedb/concept/concept.py
typedb/concept/concept_factory.py
typedb/concept/answer/__init__.py
typedb/concept/answer/concept_document_iterator.py
typedb/concept/answer/concept_row.py
typedb/concept/answer/concept_row_iterator.py
typedb/concept/answer/ok_query_answer.py
typedb/concept/answer/query_answer.py
typedb/concept/answer/query_answer_factory.py
typedb/concept/instance/__init__.py
typedb/concept/instance/attribute.py
typedb/concept/instance/entity.py
typedb_driver-3.5.5.dist-info/METADATA
typedb_driver-3.5.5.dist-info/WHEEL
typedb_driver-3.5.5.dist-info/top_level.txt
typedb_driver-3.5.5.dist-info/RECORD
