Metadata-Version: 2.1
Name: typedb-driver
Version: 3.5.5
Summary: TypeDB Driver for Python
Home-page: https://github.com/typedb/typedb-driver
Author: TypeDB Community
Author-email: community@typedb.com
License: Apache-2.0
Keywords: typedb database graph knowledgebase knowledge-engineering
Classifier: Programming Language :: Python
Classifier: Programming Language :: Python :: 3.11
Classifier: License :: OSI Approved :: Apache Software License
Classifier: Operating System :: OS Independent
Classifier: Intended Audience :: Developers
Classifier: Intended Audience :: Science/Research
Classifier: Environment :: Console
Classifier: Topic :: Database :: Front-Ends
Requires-Python: >0
Requires-Dist: parse (==1.18.0)
